skald_sdk/__init__.py
skald_sdk/client.py
skald_sdk/types.py
skald_sdk-0.3.1.dist-info/licenses/LICENSE
skald_sdk-0.3.1.dist-info/METADATA
skald_sdk-0.3.1.dist-info/WHEEL
skald_sdk-0.3.1.dist-info/top_level.txt
skald_sdk-0.3.1.dist-info/RECORD
