Metadata-Version: 2.4
Name: skald-sdk
Version: 0.3.1
Summary: Official Python SDK for Skald
Author-email: Skald Labs <support@useskald.com>
License: MIT
Project-URL: Homepage, https://useskald.com
Project-URL: Documentation, https://docs.useskald.com
Project-URL: Repository, https://github.com/skald-labs/skald-python
Project-URL: Bug Tracker, https://github.com/skald-labs/skald-python/issues
Keywords: skald,knowledge management,ai,rag,semantic search
Classifier: Development Status :: 4 - Beta
Classifier: Intended Audience :: Developers
Classifier: License :: OSI Approved :: MIT License
Classifier: Programming Language :: Python :: 3
Classifier: Programming Language :: Python :: 3.8
Classifier: Programming Language :: Python :: 3.9
Classifier: Programming Language :: Python :: 3.10
Classifier: Programming Language :: Python :: 3.11
Classifier: Programming Language :: Python :: 3.12
Requires-Python: >=3.8
License-File: LICENSE
Requires-Dist: httpx>=0.24.0
Requires-Dist: typing-extensions>=4.5.0; python_version < "3.10"
Provides-Extra: dev
Requires-Dist: pytest>=7.0.0; extra == "dev"
Requires-Dist: pytest-asyncio>=0.21.0; extra == "dev"
Requires-Dist: pytest-mock>=3.10.0; extra == "dev"
Requires-Dist: pytest-cov>=4.0.0; extra == "dev"
Requires-Dist: black>=23.0.0; extra == "dev"
Requires-Dist: mypy>=1.0.0; extra == "dev"
Requires-Dist: ruff>=0.1.0; extra == "dev"
Requires-Dist: twine>=6.1.0; extra == "dev"
Dynamic: license-file
